FRB-1.1.4.dist-info/DESCRIPTION.rst
FRB-1.1.4.dist-info/METADATA
FRB-1.1.4.dist-info/RECORD
FRB-1.1.4.dist-info/WHEEL
FRB-1.1.4.dist-info/metadata.json
FRB-1.1.4.dist-info/top_level.txt
fred/__init__.py
fred/config.py
fred/clients/__init__.py
fred/clients/categories.py
fred/clients/eseries.py
fred/clients/releases.py
fred/clients/sources.py
fred/clients/tags.py
fred/helpers/__init__.py
fred/utils/__init__.py
