Metadata-Version: 2.0
Name: FRB
Version: 1.1.4
Summary: Federal Reserve Economic Data (FRED)
Home-page: https://github.com/avelkoski/FRB
Author: Aleksandar Velkoski
Author-email: avelkoski@ltu.edu
License: MIT
Download-URL: https://github.com/avelkoski/FRB/archive/master.zip
Keywords: macroeconomics microeconomics finance fred alfred api federal reserve bank economics data
Platform: UNKNOWN
Classifier: Development Status :: 4 - Beta
Classifier: Intended Audience :: Developers
Classifier: Topic :: Software Development
Classifier: License :: OSI Approved :: MIT License
Classifier: Programming Language :: Python :: 2
Classifier: Programming Language :: Python :: 2.6
Classifier: Programming Language :: Python :: 2.7
Classifier: Programming Language :: Python :: 3
Classifier: Programming Language :: Python :: 3.2
Classifier: Programming Language :: Python :: 3.3
Classifier: Programming Language :: Python :: 3.4
Classifier: Programming Language :: Python :: 3.5
Requires-Dist: pandas
